simetuc/__init__.py
simetuc/commandline.py
simetuc/lattice.py
simetuc/odesolver.py
simetuc/odesolver_assimulo.py
simetuc/optimize.py
simetuc/plotter.py
simetuc/precalculate.py
simetuc/settings.py
simetuc/settings_config.py
simetuc/simulations.py
simetuc/util.py
simetuc/value.py
simetuc/config/log_config.cfg
simetuc/config/settings.cfg
simetuc-1.8.2.dist-info/METADATA
simetuc-1.8.2.dist-info/RECORD
simetuc-1.8.2.dist-info/WHEEL
simetuc-1.8.2.dist-info/entry_points.txt
simetuc-1.8.2.dist-info/top_level.txt
