Metadata-Version: 2.1
Name: simetuc
Version: 1.8.2
Summary: simetuc: Simulating Energy Transfer and Upconversion
Home-page: https://github.com/pedvide/simetuc
Author: Pedro Villanueva Delgado
Author-email: pedvide@gmail.com
License: MIT
Keywords: physics chemistry rate equations
Platform: UNKNOWN
Classifier: Development Status :: 5 - Production/Stable
Classifier: Intended Audience :: Science/Research
Classifier: Topic :: Scientific/Engineering :: Chemistry
Classifier: Topic :: Scientific/Engineering :: Physics
Classifier: Operating System :: MacOS :: MacOS X
Classifier: Operating System :: Microsoft :: Windows
Classifier: Operating System :: POSIX
Classifier: License :: OSI Approved :: MIT License
Classifier: Programming Language :: Python :: 3.6
Provides-Extra: test
Requires-Dist: ase (>=3.9)
Requires-Dist: matplotlib (>=1.5)
Requires-Dist: numpy (>=1.11)
Requires-Dist: scipy (>=0.18)
Requires-Dist: tqdm (>=4.8)
Requires-Dist: colorama
Requires-Dist: ruamel.yaml
Requires-Dist: h5py (>=2.6)
Requires-Dist: numba
Requires-Dist: lmfit
Requires-Dist: settings-parser
Requires-Dist: docopt
Provides-Extra: test
Requires-Dist: pytest; extra == 'test'
Requires-Dist: pytest-cov; extra == 'test'
Requires-Dist: pytest-mock; extra == 'test'
Requires-Dist: pytest-xdist; extra == 'test'
Requires-Dist: python-coveralls; extra == 'test'
Requires-Dist: flake8; extra == 'test'
Requires-Dist: mypy; extra == 'test'
